emt/__init__.py
emt/cli.py
emt/energy_meter.py
emt/collector/Cargo.toml
emt/collector/.vscode/settings.json
emt/collector/src/main.rs
emt/collector/src/power_groups/dummy.rs
emt/collector/src/power_groups/errors.rs
emt/collector/src/power_groups/mod.rs
emt/collector/src/power_groups/rapl.rs
emt/collector/src/power_groups/tracker.rs
emt/power_groups/__init__.py
emt/power_groups/nvidia_gpu.py
emt/power_groups/power_group.py
emt/power_groups/rapl_soc_cpu.py
emt/utils/__init__.py
emt/utils/gui.py
emt/utils/logger.py
emt/utils/powergroup_utils.py
emt/utils/trace_recorders.py
emt-0.0.4.dist-info/licenses/LICENSE
emt-0.0.4.dist-info/METADATA
emt-0.0.4.dist-info/WHEEL
emt-0.0.4.dist-info/entry_points.txt
emt-0.0.4.dist-info/top_level.txt
emt-0.0.4.dist-info/RECORD
