Metadata-Version: 2.4
Name: emt
Version: 0.0.4
Summary: A tool for granular energy measurement, empowering digital sustainability in machine learning and AI workflows.
Author-email: Rameez Ismail <rameez.ismail@philips.com>
License-Expression: MIT
Project-URL: Repository, https://github.com/FairCompute/energy-monitoring-tool
Keywords: deep-learning,power,energy,carbon,sustainability,emt
Requires-Python: >=3.10
License-File: LICENSE
Requires-Dist: psutil
Requires-Dist: numpy
Requires-Dist: pandas
Requires-Dist: pynvml
Requires-Dist: tabulate
Requires-Dist: click
Provides-Extra: dev
Requires-Dist: black; extra == "dev"
Requires-Dist: pytest; extra == "dev"
Requires-Dist: pytest-asyncio; extra == "dev"
Dynamic: license-file
